Metadata-Version: 2.4
Name: heimdall-mcp
Version: 0.3.7
Summary: Persistent, project-aware, long-term memory for AI coding assistants
Author: Lucas Castro
License: Apache 2.0
Keywords: ai,memory,cognitive,llm,mcp,quadrant,persistent,session,chat
Classifier: Development Status :: 4 - Beta
Classifier: Intended Audience :: Developers
Classifier: License :: OSI Approved :: Apache Software License
Classifier: Operating System :: OS Independent
Classifier: Programming Language :: Python :: 3
Classifier: Programming Language :: Python :: 3.11
Classifier: Programming Language :: Python :: 3.12
Classifier: Programming Language :: Python :: 3.13
Classifier: Topic :: Scientific/Engineering :: Artificial Intelligence
Classifier: Topic :: Software Development :: Libraries :: Python Modules
Classifier: Topic :: Utilities
Requires-Python: >=3.11
Requires-Dist: onnxruntime>=1.16.0
Requires-Dist: tokenizers>=0.21.0
Requires-Dist: qdrant-client>=1.7.0
Requires-Dist: numpy>=1.24.0
Requires-Dist: loguru>=0.7.0
Requires-Dist: python-dotenv>=1.0.0
Requires-Dist: pydantic>=2.0.0
Requires-Dist: typer>=0.9.0
Requires-Dist: rich>=13.0.0
Requires-Dist: docker>=6.0.0
Requires-Dist: psutil>=5.9.0
Requires-Dist: requests>=2.31.0
Requires-Dist: prompt-toolkit>=3.0.0
Requires-Dist: platformdirs>=3.0.0
Requires-Dist: portalocker>=2.7.0
Requires-Dist: mcp>=1.4.0
Requires-Dist: types-PyYAML
Requires-Dist: types-requests
Requires-Dist: GitPython
Requires-Dist: spacy
Requires-Dist: vaderSentiment
Requires-Dist: nrclex>=3.0.0
Provides-Extra: dev
Requires-Dist: ruff>=0.1.0; extra == "dev"
Requires-Dist: mypy>=1.5.0; extra == "dev"
Requires-Dist: black>=23.0.0; extra == "dev"
Requires-Dist: pytest>=7.0.0; extra == "dev"
Requires-Dist: pytest-cov>=4.0.0; extra == "dev"
Requires-Dist: pytest-asyncio>=0.21.0; extra == "dev"
Requires-Dist: pre-commit>=3.0.0; extra == "dev"
Requires-Dist: pip-tools>=7.0.0; extra == "dev"
Provides-Extra: test
Requires-Dist: pytest>=7.0.0; extra == "test"
Requires-Dist: pytest-cov>=4.0.0; extra == "test"
Requires-Dist: pytest-asyncio>=0.21.0; extra == "test"
Requires-Dist: pytest-mock>=3.10.0; extra == "test"
